{
  "tradeName": "Stella Asset 株式会社",
  "licenseNumber": "Real Estate Specified Joint Enterprise\nOsaka Governor License No. 22",
  "licenseType": "Type I, Type II, and Electronic Transaction Operations",
  "representative": "代表取締役　谷中　譲",
  "headOffice": "2-1-12 Tenma, Kita-ku, Osaka-shi, Osaka",
  "tel": "06-6940-4777",
  "established": "December 11, 2012",
  "business": "Real estate specified joint enterprise, e-commerce, and related businesses",
  "manager": "Ai Setoguchi\nCertified Real Estate Consulting Master",
  "copyright": "© Stella Asset Co., Ltd. All Rights Reserved.",
  "links": [
    {
      "title": "Terms of Use",
      "icon": "",
      "url": "https://stellavia.co.jp/terms_conditions.pdf"
    },
    {
      "title": "Electronic Delivery",
      "icon": "",
      "url": "https://stellavia.co.jp/electronic_information.pdf"
    },
    {
      "title": "Privacy Policy",
      "icon": "",
      "url": "https://stellavia.co.jp/personal_information.pdf"
    },
    {
      "title": "Solicitation Policy",
      "icon": "",
      "url": "https://stellavia.co.jp/solicitation_policy.pdf"
    },
    {
      "title": "Anti-Social Forces Policy",
      "icon": "",
      "url": "https://stellavia.co.jp/antisocialrule.pdf"
    }
  ]
}
